dummy_useragent/__init__.py
dummy_useragent/dummy.py
dummy_useragent/useragent.py
test/__init__.py
test/test_dummy.py
dummy_useragent-0.7.dist-info/LICENSE
dummy_useragent-0.7.dist-info/METADATA
dummy_useragent-0.7.dist-info/WHEEL
dummy_useragent-0.7.dist-info/top_level.txt
dummy_useragent-0.7.dist-info/RECORD
