Metadata-Version: 2.1
Name: dummy-useragent
Version: 0.7
Summary: random useragent without network
Home-page: https://github.com/Hexmagic/dummy_useragent.git
Author: Hexmagic
Author-email: 191440042@qq.com
License: GNU General Public License v3.0
Platform: UNKNOWN
Classifier: Programming Language :: Python :: 3.5
Classifier: Operating System :: OS Independent
Requires-Dist: aiohttp
